MANIFEST.in
setup.py
picraftzero/__init__.py
picraftzero/__main__.py
picraftzero/admin.py
picraftzero/config.py
picraftzero/log.py
picraftzero/servers.py
picraftzero/utils.py
picraftzero/version.py
picraftzero/zero.py
picraftzero.egg-info/PKG-INFO
picraftzero.egg-info/SOURCES.txt
picraftzero.egg-info/dependency_links.txt
picraftzero.egg-info/not-zip-safe
picraftzero.egg-info/requires.txt
picraftzero.egg-info/top_level.txt
picraftzero/inputs/__init__.py
picraftzero/inputs/joystick.py
picraftzero/interfaces/__init__.py
picraftzero/interfaces/hardware/__init__.py
picraftzero/interfaces/hardware/providers.py
picraftzero/providers/__init__.py
picraftzero/providers/motor/__init__.py
picraftzero/providers/motor/piconzero.py
picraftzero/providers/motor/pimoroni.py
picraftzero/providers/servo/__init__.py
picraftzero/providers/servo/piconzero.py
picraftzero/providers/servo/pimoroniservo.py
picraftzero/resources/config/picraftzero.cfg
picraftzero/resources/config/picraftzero.service
picraftzero/resources/config/picraftzero_snippet_uv4l.cfg
picraftzero/resources/config/uv4l-raspicam.conf
picraftzero/resources/www/favicon.ico
picraftzero/resources/www/index.html
picraftzero/resources/www/manifest.json
picraftzero/resources/www/css/addtohomescreen.css
picraftzero/resources/www/css/app.css
picraftzero/resources/www/css/font-awesome/HELP-US-OUT.txt
picraftzero/resources/www/css/font-awesome/css/font-awesome.css
picraftzero/resources/www/css/font-awesome/css/font-awesome.min.css
picraftzero/resources/www/css/font-awesome/fonts/FontAwesome.otf
picraftzero/resources/www/css/font-awesome/fonts/fontawesome-webfont.eot
picraftzero/resources/www/css/font-awesome/fonts/fontawesome-webfont.svg
picraftzero/resources/www/css/font-awesome/fonts/fontawesome-webfont.ttf
picraftzero/resources/www/css/font-awesome/fonts/fontawesome-webfont.woff
picraftzero/resources/www/css/font-awesome/fonts/fontawesome-webfont.woff2
picraftzero/resources/www/css/font-awesome/less/animated.less
picraftzero/resources/www/css/font-awesome/less/bordered-pulled.less
picraftzero/resources/www/css/font-awesome/less/core.less
picraftzero/resources/www/css/font-awesome/less/fixed-width.less
