Metadata-Version: 1.1
Name: picraftzero
Version: 0.2.13
Summary: A library for building universal controls for robots
Home-page: https://www.thebubbleworks.com/picraftzero
Author: Wayne Keenan
Author-email: wayne@thebubbleworks.com
License: MIT
Platform: Raspberry Pi
Platform: Linux
Platform: Mac
Classifier: Development Status :: 4 - Beta
Classifier: Programming Language :: Python :: 3
Classifier: Environment :: Console
Classifier: Environment :: Web Environment
Classifier: Intended Audience :: End Users/Desktop
Classifier: Intended Audience :: Developers
Classifier: Operating System :: MacOS :: MacOS X
Classifier: Operating System :: POSIX
Classifier: Topic :: Software Development :: Libraries :: Python Modules
